{
    "schemaVersion": 1,
    "id": "shuffle",
    "version": "${version}",
    "name": "Shuffle",
    "description": "Place random blocks from your hotbar with ease!",
    "authors": [
        "Trikzon"
    ],
    "contact": {
        "homepage": "https://www.curseforge.com/minecraft/mc-mods/shuffle-fabric",
        "sources": "https://github.com/trikzon/shuffle"
    },
    "license": "MIT",
    "icon": "assets/shuffle/icon.png",
    "environment": "*",
    "entrypoints": {
        "client": [
            "com.trikzon.shuffle.fabric.client.ShuffleFabricClient"
        ]
    },
    "mixins": [
    ],
    "depends": {
        "fabricloader": ">=0.11",
        "fabric": "*",
        "minecraft": "1.17.x"
    },
    "suggests": {
        "flamingo": "*"
    },
    "custom": {
        "modmenu": {
            "links": {
                "shuffle.discord": "https://discord.gg/aqXkvbJ"
            }
        }
    }
}